{
    "mc": {
        "weapon1188882_1_3d": {
            "frameRate": 20,
            "frames": [
                {
                    "res": "00015.png",
                    "x": -44.0,
                    "y": -76.0
                },
                {
                    "res": "00016.png",
                    "x": -52.0,
                    "y": -72.0
                },
                {
                    "res": "00017.png",
                    "x": -39.0,
                    "y": -218.0
                },
                {
                    "res": "00018.png",
                    "x": -117.0,
                    "y": -83.0
                },
                {
                    "res": "00019.png",
                    "x": -143.0,
                    "y": -124.0
                }
            ]
        }
    },
    "res": {
        "00015.png": {
            "x": 0,
            "y": 0,
            "w": 139,
            "h": 127
        },
        "00016.png": {
            "x": 139,
            "y": 0,
            "w": 138,
            "h": 128
        },
        "00017.png": {
            "x": 277,
            "y": 0,
            "w": 115,
            "h": 175
        },
        "00018.png": {
            "x": 392,
            "y": 0,
            "w": 156,
            "h": 76
        },
        "00019.png": {
            "x": 548,
            "y": 0,
            "w": 87,
            "h": 127
        }
    }
}