{"mc":{
	"weapon919_1_1a":{
		"frameRate":15,
		"events":[
			
			],
		"frames":[
			
			{
			"res":"3AB1A6DE",
			"x":-24,
			"y":-168
			},
			{
			"res":"4B520E75",
			"x":-182,
			"y":-122
			},
			{
			"res":"E1350CD0",
			"x":-139,
			"y":-128
			},
			{
			"res":"DF53B815",
			"x":4,
			"y":-184
			},
			{
			"res":"F545D00A",
			"x":18,
			"y":-116
			},
			{
			"res":"85902458",
			"x":7,
			"y":-102
			},
			{
			"res":"428BE1A",
			"x":-36,
			"y":-133
			}
			]
}},
	"res":{
		"85902458":{"x":72,"y":101,"w":71,"h":97},
		"DF53B815":{"x":0,"y":101,"w":72,"h":113},
		"3AB1A6DE":{"x":361,"y":0,"w":107,"h":135},
		"E1350CD0":{"x":0,"y":0,"w":177,"h":101},
		"428BE1A":{"x":177,"y":97,"w":105,"h":95},
		"4B520E75":{"x":177,"y":0,"w":184,"h":97},
		"F545D00A":{"x":282,"y":97,"w":76,"h":108}
	}}