{
    "mc": {
        "weapon975_1_0d": {
            "frameRate": 20,
            "frames": [
                {
                    "res": "00000.png",
                    "x": 3.0,
                    "y": -134.0
                },
                {
                    "res": "00001.png",
                    "x": -2.0,
                    "y": -150.0
                },
                {
                    "res": "00002.png",
                    "x": -26.0,
                    "y": -152.0
                },
                {
                    "res": "00003.png",
                    "x": -55.0,
                    "y": -42.0
                },
                {
                    "res": "00004.png",
                    "x": -34.0,
                    "y": 27.0
                }
            ]
        }
    },
    "res": {
        "00000.png": {
            "x": 0,
            "y": 0,
            "w": 49,
            "h": 134
        },
        "00001.png": {
            "x": 49,
            "y": 0,
            "w": 98,
            "h": 113
        },
        "00002.png": {
            "x": 147,
            "y": 0,
            "w": 67,
            "h": 96
        },
        "00003.png": {
            "x": 214,
            "y": 0,
            "w": 103,
            "h": 90
        },
        "00004.png": {
            "x": 317,
            "y": 0,
            "w": 111,
            "h": 78
        }
    }
}