{"mc":{
	"weapon928_0_2r":{
		"frameRate":12,
		"events":[
			
			],
		"frames":[
			
			{
			"res":"7409B121",
			"x":-44,
			"y":-70
			},
			{
			"res":"78D38324",
			"x":-49,
			"y":-65
			},
			{
			"res":"BC49473D",
			"x":-41,
			"y":-62
			},
			{
			"res":"2DA5F1C1",
			"x":-17,
			"y":-97
			},
			{
			"res":"31D7D37",
			"x":-3,
			"y":-173
			},
			{
			"res":"2AC85207",
			"x":8,
			"y":-210
			},
			{
			"res":"78E1F15B",
			"x":-8,
			"y":-176
			},
			{
			"res":"21F87078",
			"x":-36,
			"y":-89
			}
			]
}},
	"res":{
		"31D7D37":{"x":0,"y":0,"w":130,"h":140},
		"21F87078":{"x":179,"y":208,"w":182,"h":59},
		"BC49473D":{"x":179,"y":147,"w":178,"h":61},
		"7409B121":{"x":0,"y":267,"w":186,"h":49},
		"2AC85207":{"x":423,"y":0,"w":70,"h":175},
		"2DA5F1C1":{"x":0,"y":147,"w":179,"h":66},
		"78D38324":{"x":250,"y":0,"w":173,"h":80},
		"78E1F15B":{"x":130,"y":0,"w":120,"h":147}
	}}