{
    "mc": {
        "weapon984_0_1a": {
            "frameRate": 20,
            "frames": [
                {
                    "res": "00009.png",
                    "x": -135.0,
                    "y": -116.0
                },
                {
                    "res": "00010.png",
                    "x": -194.0,
                    "y": -101.0
                },
                {
                    "res": "00011.png",
                    "x": -146.0,
                    "y": -94.0
                },
                {
                    "res": "00012.png",
                    "x": -28.0,
                    "y": -118.0
                },
                {
                    "res": "00013.png",
                    "x": 9.0,
                    "y": -92.0
                },
                {
                    "res": "00014.png",
                    "x": 2.0,
                    "y": -97.0
                },
                {
                    "res": "00015.png",
                    "x": 5.0,
                    "y": -103.0
                },
                {
                    "res": "00008.png",
                    "x": 7.0,
                    "y": -153.0
                }
            ]
        }
    },
    "res": {
        "00008.png": {
            "x": 0,
            "y": 0,
            "w": 62,
            "h": 139
        },
        "00009.png": {
            "x": 62,
            "y": 0,
            "w": 158,
            "h": 93
        },
        "00010.png": {
            "x": 220,
            "y": 0,
            "w": 189,
            "h": 70
        },
        "00011.png": {
            "x": 409,
            "y": 0,
            "w": 167,
            "h": 67
        },
        "00012.png": {
            "x": 576,
            "y": 0,
            "w": 107,
            "h": 60
        },
        "00013.png": {
            "x": 683,
            "y": 0,
            "w": 140,
            "h": 69
        },
        "00014.png": {
            "x": 823,
            "y": 0,
            "w": 150,
            "h": 80
        },
        "00015.png": {
            "x": 973,
            "y": 0,
            "w": 153,
            "h": 100
        }
    }
}