{"mc":{
	"weapon929_0_1a":{
		"frameRate":15,
		"events":[
			
			],
		"frames":[
			
			{
			"res":"AC8F3B73",
			"x":-31,
			"y":-166
			},
			{
			"res":"9CC1BD3A",
			"x":-186,
			"y":-128
			},
			{
			"res":"74F07B70",
			"x":-137,
			"y":-145
			},
			{
			"res":"8790BB8C",
			"x":5,
			"y":-179
			},
			{
			"res":"B0207473",
			"x":8,
			"y":-111
			},
			{
			"res":"97A60641",
			"x":-3,
			"y":-109
			},
			{
			"res":"6407C45",
			"x":-37,
			"y":-133
			}
			]
}},
	"res":{
		"8790BB8C":{"x":0,"y":120,"w":78,"h":122},
		"6407C45":{"x":325,"y":110,"w":120,"h":113},
		"AC8F3B73":{"x":204,"y":110,"w":121,"h":156},
		"B0207473":{"x":426,"y":0,"w":84,"h":105},
		"97A60641":{"x":78,"y":120,"w":81,"h":112},
		"74F07B70":{"x":0,"y":0,"w":204,"h":120},
		"9CC1BD3A":{"x":204,"y":0,"w":222,"h":110}
	}}