{
    "mc": {
        "weapon981_0_0a": {
            "frameRate": 20,
            "frames": [
                {
                    "res": "00001.png",
                    "x": -133.0,
                    "y": -155.0
                },
                {
                    "res": "00002.png",
                    "x": -240.0,
                    "y": -126.0
                },
                {
                    "res": "00003.png",
                    "x": -139.0,
                    "y": -131.0
                },
                {
                    "res": "00004.png",
                    "x": -57.0,
                    "y": -180.0
                },
                {
                    "res": "00005.png",
                    "x": -132.0,
                    "y": -199.0
                },
                {
                    "res": "00006.png",
                    "x": -127.0,
                    "y": -199.0
                },
                {
                    "res": "00007.png",
                    "x": -61.0,
                    "y": -226.0
                },
                {
                    "res": "00000.png",
                    "x": -39.0,
                    "y": -276.0
                }
            ]
        }
    },
    "res": {
        "00000.png": {
            "x": 0,
            "y": 0,
            "w": 186,
            "h": 271
        },
        "00001.png": {
            "x": 186,
            "y": 0,
            "w": 203,
            "h": 194
        },
        "00002.png": {
            "x": 389,
            "y": 0,
            "w": 297,
            "h": 195
        },
        "00003.png": {
            "x": 686,
            "y": 0,
            "w": 222,
            "h": 214
        },
        "00004.png": {
            "x": 908,
            "y": 0,
            "w": 201,
            "h": 185
        },
        "00005.png": {
            "x": 1109,
            "y": 0,
            "w": 193,
            "h": 198
        },
        "00006.png": {
            "x": 1302,
            "y": 0,
            "w": 188,
            "h": 198
        },
        "00007.png": {
            "x": 1490,
            "y": 0,
            "w": 194,
            "h": 243
        }
    }
}