{"mc":{
	"weapon917_1_4r":{
		"frameRate":12,
		"events":[
			
			],
		"frames":[
			
			{
			"res":"B9E358FE",
			"x":-46,
			"y":-85
			},
			{
			"res":"2B8955D0",
			"x":-41,
			"y":-108
			},
			{
			"res":"82C00692",
			"x":-34,
			"y":-87
			},
			{
			"res":"6239BC78",
			"x":-27,
			"y":-84
			},
			{
			"res":"2FC1063",
			"x":-25,
			"y":-133
			},
			{
			"res":"B4EDE327",
			"x":-24,
			"y":-189
			},
			{
			"res":"3283B6D1",
			"x":-25,
			"y":-141
			},
			{
			"res":"53BE9689",
			"x":-27,
			"y":-89
			}
			]
}},
	"res":{
		"3283B6D1":{"x":145,"y":0,"w":59,"h":102},
		"2B8955D0":{"x":204,"y":0,"w":26,"h":194},
		"2FC1063":{"x":74,"y":0,"w":71,"h":93},
		"B9E358FE":{"x":157,"y":102,"w":31,"h":118},
		"82C00692":{"x":127,"y":102,"w":30,"h":153},
		"B4EDE327":{"x":0,"y":0,"w":74,"h":153},
		"53BE9689":{"x":0,"y":153,"w":30,"h":88},
		"6239BC78":{"x":74,"y":93,"w":53,"h":94}
	}}