{
    "mc": {
        "weapon958_0_0s": {
            "frameRate": 10,
            "frames": [
                {
                    "res": "00000.png",
                    "x": 5.0,
                    "y": -92.0
                },
                {
                    "res": "00001.png",
                    "x": 4.0,
                    "y": -93.0
                },
                {
                    "res": "00002.png",
                    "x": 4.0,
                    "y": -95.0
                },
                {
                    "res": "00003.png",
                    "x": 3.0,
                    "y": -95.0
                },
                {
                    "res": "00004.png",
                    "x": 4.0,
                    "y": -95.0
                }
            ]
        }
    },
    "res": {
        "00000.png": {
            "x": 0,
            "y": 0,
            "w": 31,
            "h": 58
        },
        "00001.png": {
            "x": 31,
            "y": 0,
            "w": 32,
            "h": 58
        },
        "00002.png": {
            "x": 63,
            "y": 0,
            "w": 32,
            "h": 59
        },
        "00003.png": {
            "x": 95,
            "y": 0,
            "w": 33,
            "h": 59
        },
        "00004.png": {
            "x": 128,
            "y": 0,
            "w": 32,
            "h": 60
        }
    }
}