{
    "mc": {
        "weapon981_0_4d": {
            "frameRate": 20,
            "frames": [
                {
                    "res": "00020.png",
                    "x": -95.0,
                    "y": -111.0
                },
                {
                    "res": "00021.png",
                    "x": -137.0,
                    "y": -116.0
                },
                {
                    "res": "00022.png",
                    "x": -75.0,
                    "y": -226.0
                },
                {
                    "res": "00023.png",
                    "x": -85.0,
                    "y": -145.0
                },
                {
                    "res": "00024.png",
                    "x": -103.0,
                    "y": -212.0
                }
            ]
        }
    },
    "res": {
        "00020.png": {
            "x": 0,
            "y": 0,
            "w": 187,
            "h": 232
        },
        "00021.png": {
            "x": 187,
            "y": 0,
            "w": 200,
            "h": 238
        },
        "00022.png": {
            "x": 387,
            "y": 0,
            "w": 241,
            "h": 193
        },
        "00023.png": {
            "x": 628,
            "y": 0,
            "w": 297,
            "h": 186
        },
        "00024.png": {
            "x": 925,
            "y": 0,
            "w": 245,
            "h": 205
        }
    }
}