{
	"mc": {
		"weapon950_0_0a": {
			"frameRate": 20,
			"frames": [
				{
					"res": "res8",
					"x": -62,
					"y": -96
				},
				{
					"res": "res7",
					"x": -131,
					"y": -52
				},
				{
					"res": "res6",
					"x": -65,
					"y": -90
				},
				{
					"res": "res5",
					"x": 27,
					"y": -123
				},
				{
					"res": "res4",
					"x": -23,
					"y": -136
				},
				{
					"res": "res3",
					"x": -23,
					"y": -136
				},
				{
					"res": "res2",
					"x": 17,
					"y": -150
				},
				{
					"res": "res1",
					"x": 32,
					"y": -189
				}
			]
		}
	},
	"res": {
		"res1": {
			"x": 0,
			"y": 0,
			"w": 47,
			"h": 144
		},
		"res2": {
			"x": 483,
			"y": 0,
			"w": 32,
			"h": 127
		},
		"res3": {
			"x": 452,
			"y": 0,
			"w": 31,
			"h": 99
		},
		"res4": {
			"x": 421,
			"y": 0,
			"w": 31,
			"h": 99
		},
		"res5": {
			"x": 395,
			"y": 0,
			"w": 26,
			"h": 41
		},
		"res6": {
			"x": 284,
			"y": 0,
			"w": 111,
			"h": 81
		},
		"res7": {
			"x": 142,
			"y": 0,
			"w": 142,
			"h": 26
		},
		"res8": {
			"x": 47,
			"y": 0,
			"w": 95,
			"h": 58
		}
	}
}