{
	"mc": {
		"weapon946_1_0c": {
			"frameRate": 20,
			"frames": [
				{
					"res": "res8",
					"x": -34,
					"y": -212
				},
				{
					"res": "res7",
					"x": -28,
					"y": -195
				},
				{
					"res": "res6",
					"x": -30,
					"y": -252
				},
				{
					"res": "res5",
					"x": -21,
					"y": -260
				},
				{
					"res": "res4",
					"x": -21,
					"y": -260
				},
				{
					"res": "res3",
					"x": 1,
					"y": -180
				},
				{
					"res": "res2",
					"x": 7,
					"y": -184
				},
				{
					"res": "res1",
					"x": 14,
					"y": -180
				}
			]
		}
	},
	"res": {
		"res1": {
			"x": 0,
			"y": 0,
			"w": 111,
			"h": 144
		},
		"res2": {
			"x": 477,
			"y": 0,
			"w": 135,
			"h": 144
		},
		"res3": {
			"x": 430,
			"y": 0,
			"w": 47,
			"h": 128
		},
		"res4": {
			"x": 373,
			"y": 0,
			"w": 57,
			"h": 191
		},
		"res5": {
			"x": 316,
			"y": 0,
			"w": 57,
			"h": 186
		},
		"res6": {
			"x": 251,
			"y": 0,
			"w": 65,
			"h": 162
		},
		"res7": {
			"x": 189,
			"y": 0,
			"w": 62,
			"h": 145
		},
		"res8": {
			"x": 111,
			"y": 0,
			"w": 78,
			"h": 183
		}
	}
}