{
	"mc": {
		"weapon957_1_1s": {
			"frameRate": 10,
			"frames": [
				{
					"res": "res5",
					"x": -35,
					"y": -123
				},
				{
					"res": "res4",
					"x": -33,
					"y": -127
				},
				{
					"res": "res3",
					"x": -33,
					"y": -128
				},
				{
					"res": "res2",
					"x": -33,
					"y": -128
				},
				{
					"res": "res1",
					"x": -32,
					"y": -124
				}
			]
		}
	},
	"res": {
		"res1": {
			"x": 500,
			"y": 0,
			"w": 128,
			"h": 115
		},
		"res2": {
			"x": 373,
			"y": 0,
			"w": 127,
			"h": 122
		},
		"res3": {
			"x": 248,
			"y": 0,
			"w": 125,
			"h": 119
		},
		"res4": {
			"x": 125,
			"y": 0,
			"w": 123,
			"h": 118
		},
		"res5": {
			"x": 0,
			"y": 0,
			"w": 125,
			"h": 117
		}
	}
}