{"mc":{
	"weapon917_1_1s":{
		"frameRate":6,
		"events":[
			
			],
		"frames":[
			
			{
			"res":"15E1A692",
			"x":-19,
			"y":-85
			},
			{
			"res":"3800CBA9",
			"x":-19,
			"y":-85
			},
			{
			"res":"C79955CC",
			"x":-19,
			"y":-85
			},
			{
			"res":"432196FE",
			"x":-19,
			"y":-88
			}
			]
}},
	"res":{
		"C79955CC":{"x":0,"y":0,"w":175,"h":89},
		"15E1A692":{"x":166,"y":89,"w":170,"h":87},
		"3800CBA9":{"x":175,"y":0,"w":173,"h":89},
		"432196FE":{"x":0,"y":89,"w":166,"h":90}
	}}