{
	"mc": {
		"weapon964_0_2d": {
			"frameRate": 20,
			"frames": [
				{
					"res": "res5",
					"x": -96,
					"y": -69
				},
				{
					"res": "res4",
					"x": -83,
					"y": -73
				},
				{
					"res": "res3",
					"x": -27,
					"y": -209
				},
				{
					"res": "res2",
					"x": -145,
					"y": -72
				},
				{
					"res": "res1",
					"x": -192,
					"y": -77
				}
			]
		}
	},
	"res": {
		"res1": {
			"x": 622,
			"y": 0,
			"w": 160,
			"h": 170
		},
		"res2": {
			"x": 526,
			"y": 0,
			"w": 96,
			"h": 103
		},
		"res3": {
			"x": 461,
			"y": 0,
			"w": 65,
			"h": 233
		},
		"res4": {
			"x": 229,
			"y": 0,
			"w": 232,
			"h": 70
		},
		"res5": {
			"x": 0,
			"y": 0,
			"w": 229,
			"h": 58
		}
	}
}