{
	"mc": {
		"weapon948_1_1s": {
			"frameRate": 10,
			"frames": [
				{
					"res": "res5",
					"x": -16,
					"y": -91
				},
				{
					"res": "res4",
					"x": -17,
					"y": -93
				},
				{
					"res": "res3",
					"x": -17,
					"y": -95
				},
				{
					"res": "res2",
					"x": -15,
					"y": -94
				},
				{
					"res": "res1",
					"x": -16,
					"y": -93
				}
			]
		}
	},
	"res": {
		"res1": {
			"x": 502,
			"y": 0,
			"w": 126,
			"h": 83
		},
		"res2": {
			"x": 377,
			"y": 0,
			"w": 125,
			"h": 84
		},
		"res3": {
			"x": 251,
			"y": 0,
			"w": 126,
			"h": 85
		},
		"res4": {
			"x": 125,
			"y": 0,
			"w": 126,
			"h": 84
		},
		"res5": {
			"x": 0,
			"y": 0,
			"w": 125,
			"h": 83
		}
	}
}