{"mc":{
	"body923_1_3c":{
		"frameRate":15,
		"events":[
			
			],
		"frames":[
			
			{
			"res":"C0D8FFE4",
			"x":-33,
			"y":-108
			},
			{
			"res":"55848DC",
			"x":-27,
			"y":-109
			},
			{
			"res":"4DE9E7E4",
			"x":-28,
			"y":-110
			},
			{
			"res":"52476D01",
			"x":-28,
			"y":-113
			},
			{
			"res":"4349257",
			"x":-28,
			"y":-112
			},
			{
			"res":"267B06A0",
			"x":-26,
			"y":-108
			},
			{
			"res":"57354F15",
			"x":-38,
			"y":-98
			}
			]
}},
	"res":{
		"4349257":{"x":182,"y":0,"w":52,"h":117},
		"57354F15":{"x":0,"y":0,"w":72,"h":105},
		"4DE9E7E4":{"x":0,"y":105,"w":52,"h":115},
		"55848DC":{"x":52,"y":113,"w":51,"h":114},
		"52476D01":{"x":130,"y":0,"w":52,"h":118},
		"267B06A0":{"x":182,"y":117,"w":51,"h":113},
		"C0D8FFE4":{"x":72,"y":0,"w":58,"h":113}
	}}