{"mc": {"body962_1_4r": {"frameRate": 12, "frames": [{"res": "00064", "x": -38, "y": -126}, {"res": "00066", "x": -38, "y": -126}, {"res": "00068", "x": -40, "y": -117}, {"res": "00070", "x": -41, "y": -117}, {"res": "00072", "x": -40, "y": -120}, {"res": "00074", "x": -38, "y": -122}, {"res": "00076", "x": -38, "y": -118}, {"res": "00078", "x": -37, "y": -121}]}}, "res": {"00064": {"x": 0, "y": 0, "w": 73, "h": 145}, "00066": {"x": 73, "y": 0, "w": 78, "h": 165}, "00068": {"x": 151, "y": 0, "w": 85, "h": 144}, "00070": {"x": 236, "y": 0, "w": 88, "h": 136}, "00072": {"x": 324, "y": 0, "w": 77, "h": 139}, "00074": {"x": 401, "y": 0, "w": 75, "h": 155}, "00076": {"x": 476, "y": 0, "w": 75, "h": 148}, "00078": {"x": 551, "y": 0, "w": 74, "h": 142}}}