{"mc":{"body926_0_0a":{"frameRate":15,"frames":[{"res":"122","x":-54,"y":-108},{"res":"123","x":-66,"y":-108},{"res":"124","x":-58,"y":-108},{"res":"125","x":-55,"y":-122},{"res":"126","x":-53,"y":-108},{"res":"127","x":-54,"y":-108},{"res":"601","x":-54,"y":-108}]}},"res":{"122":{"x":0,"y":0,"w":128,"h":161},"123":{"x":128,"y":0,"w":138,"h":161},"124":{"x":266,"y":0,"w":129,"h":161},"125":{"x":395,"y":0,"w":125,"h":175},"126":{"x":520,"y":0,"w":124,"h":167},"127":{"x":644,"y":0,"w":126,"h":161},"601":{"x":770,"y":0,"w":129,"h":161}}}