{
	"mc": {
		"body943_0_2c": {
			"frameRate": 20,
			"frames": [
				{
					"res": "res8",
					"x": -66,
					"y": -118
				},
				{
					"res": "res7",
					"x": -66,
					"y": -118
				},
				{
					"res": "res6",
					"x": -56,
					"y": -143
				},
				{
					"res": "res5",
					"x": -54,
					"y": -142
				},
				{
					"res": "res4",
					"x": -54,
					"y": -142
				},
				{
					"res": "res3",
					"x": -55,
					"y": -119
				},
				{
					"res": "res2",
					"x": -60,
					"y": -123
				},
				{
					"res": "res1",
					"x": -70,
					"y": -120
				}
			]
		}
	},
	"res": {
		"res1": {
			"x": 0,
			"y": 0,
			"w": 128,
			"h": 156
		},
		"res2": {
			"x": 773,
			"y": 0,
			"w": 115,
			"h": 158
		},
		"res3": {
			"x": 662,
			"y": 0,
			"w": 111,
			"h": 154
		},
		"res4": {
			"x": 558,
			"y": 0,
			"w": 104,
			"h": 177
		},
		"res5": {
			"x": 455,
			"y": 0,
			"w": 103,
			"h": 177
		},
		"res6": {
			"x": 354,
			"y": 0,
			"w": 101,
			"h": 178
		},
		"res7": {
			"x": 240,
			"y": 0,
			"w": 114,
			"h": 153
		},
		"res8": {
			"x": 128,
			"y": 0,
			"w": 112,
			"h": 153
		}
	}
}