{
    "mc": {
        "body2208888_0_0r": {
            "frameRate": 12,
            "frames": [
                {
                    "res": "00000.png",
                    "x": -87.0,
                    "y": -153.0
                },
                {
                    "res": "00002.png",
                    "x": -70.0,
                    "y": -153.0
                },
                {
                    "res": "00004.png",
                    "x": -82.0,
                    "y": -152.0
                },
                {
                    "res": "00006.png",
                    "x": -96.0,
                    "y": -152.0
                },
                {
                    "res": "00008.png",
                    "x": -110.0,
                    "y": -155.0
                },
                {
                    "res": "00010.png",
                    "x": -121.0,
                    "y": -155.0
                },
                {
                    "res": "00012.png",
                    "x": -109.0,
                    "y": -152.0
                },
                {
                    "res": "00014.png",
                    "x": -93.0,
                    "y": -149.0
                }
            ]
        }
    },
    "res": {
        "00000.png": {
            "x": 0,
            "y": 0,
            "w": 192,
            "h": 197
        },
        "00002.png": {
            "x": 192,
            "y": 0,
            "w": 183,
            "h": 191
        },
        "00004.png": {
            "x": 375,
            "y": 0,
            "w": 180,
            "h": 193
        },
        "00006.png": {
            "x": 555,
            "y": 0,
            "w": 189,
            "h": 192
        },
        "00008.png": {
            "x": 744,
            "y": 0,
            "w": 196,
            "h": 189
        },
        "00010.png": {
            "x": 940,
            "y": 0,
            "w": 200,
            "h": 187
        },
        "00012.png": {
            "x": 1140,
            "y": 0,
            "w": 194,
            "h": 194
        },
        "00014.png": {
            "x": 1334,
            "y": 0,
            "w": 188,
            "h": 197
        }
    }
}