{"mc": {"body925_0_0s": {"frameRate": 10, "frames": [{"res": "00000", "x": -56, "y": -126}, {"res": "00001", "x": -63, "y": -128}, {"res": "00002", "x": -57, "y": -127}, {"res": "00003", "x": -51, "y": -125}, {"res": "00004", "x": -50, "y": -124}]}}, "res": {"00000": {"x": 0, "y": 0, "w": 110, "h": 151}, "00001": {"x": 110, "y": 0, "w": 123, "h": 154}, "00002": {"x": 233, "y": 0, "w": 115, "h": 153}, "00003": {"x": 348, "y": 0, "w": 111, "h": 162}, "00004": {"x": 459, "y": 0, "w": 99, "h": 157}}}