{
	"mc": {
		"body967_1_2r": {
			"frameRate": 12,
			"frames": [
				{
					"res": "res8",
					"x": -99,
					"y": -132
				},
				{
					"res": "res7",
					"x": -93,
					"y": -131
				},
				{
					"res": "res6",
					"x": -89,
					"y": -130
				},
				{
					"res": "res5",
					"x": -109,
					"y": -130
				},
				{
					"res": "res4",
					"x": -109,
					"y": -132
				},
				{
					"res": "res3",
					"x": -102,
					"y": -138
				},
				{
					"res": "res2",
					"x": -90,
					"y": -130
				},
				{
					"res": "res1",
					"x": -93,
					"y": -130
				}
			]
		}
	},
	"res": {
		"res1": {
			"x": 1095,
			"y": 0,
			"w": 146,
			"h": 183
		},
		"res2": {
			"x": 945,
			"y": 0,
			"w": 150,
			"h": 173
		},
		"res3": {
			"x": 786,
			"y": 0,
			"w": 159,
			"h": 173
		},
		"res4": {
			"x": 620,
			"y": 0,
			"w": 166,
			"h": 161
		},
		"res5": {
			"x": 452,
			"y": 0,
			"w": 168,
			"h": 157
		},
		"res6": {
			"x": 301,
			"y": 0,
			"w": 151,
			"h": 147
		},
		"res7": {
			"x": 154,
			"y": 0,
			"w": 147,
			"h": 154
		},
		"res8": {
			"x": 0,
			"y": 0,
			"w": 154,
			"h": 170
		}
	}
}