{
	"mc": {
		"body957_0_4r": {
			"frameRate": 12,
			"frames": [
				{
					"res": "res8",
					"x": -66,
					"y": -143
				},
				{
					"res": "res7",
					"x": -61,
					"y": -143
				},
				{
					"res": "res6",
					"x": -59,
					"y": -143
				},
				{
					"res": "res5",
					"x": -62,
					"y": -138
				},
				{
					"res": "res4",
					"x": -59,
					"y": -142
				},
				{
					"res": "res3",
					"x": -58,
					"y": -142
				},
				{
					"res": "res2",
					"x": -61,
					"y": -139
				},
				{
					"res": "res1",
					"x": -60,
					"y": -141
				}
			]
		}
	},
	"res": {
		"res1": {
			"x": 842,
			"y": 0,
			"w": 121,
			"h": 176
		},
		"res2": {
			"x": 720,
			"y": 0,
			"w": 122,
			"h": 171
		},
		"res3": {
			"x": 603,
			"y": 0,
			"w": 117,
			"h": 170
		},
		"res4": {
			"x": 486,
			"y": 0,
			"w": 117,
			"h": 175
		},
		"res5": {
			"x": 363,
			"y": 0,
			"w": 123,
			"h": 168
		},
		"res6": {
			"x": 243,
			"y": 0,
			"w": 120,
			"h": 173
		},
		"res7": {
			"x": 125,
			"y": 0,
			"w": 118,
			"h": 180
		},
		"res8": {
			"x": 0,
			"y": 0,
			"w": 125,
			"h": 183
		}
	}
}