{
	"mc": {
		"body943_1_2r": {
			"frameRate": 12,
			"frames": [
				{
					"res": "res8",
					"x": -70,
					"y": -133
				},
				{
					"res": "res7",
					"x": -83,
					"y": -129
				},
				{
					"res": "res6",
					"x": -68,
					"y": -128
				},
				{
					"res": "res5",
					"x": -59,
					"y": -128
				},
				{
					"res": "res4",
					"x": -70,
					"y": -130
				},
				{
					"res": "res3",
					"x": -88,
					"y": -131
				},
				{
					"res": "res2",
					"x": -76,
					"y": -131
				},
				{
					"res": "res1",
					"x": -59,
					"y": -128
				}
			]
		}
	},
	"res": {
		"res1": {
			"x": 896,
			"y": 0,
			"w": 116,
			"h": 162
		},
		"res2": {
			"x": 764,
			"y": 0,
			"w": 132,
			"h": 164
		},
		"res3": {
			"x": 607,
			"y": 0,
			"w": 157,
			"h": 165
		},
		"res4": {
			"x": 489,
			"y": 0,
			"w": 118,
			"h": 158
		},
		"res5": {
			"x": 380,
			"y": 0,
			"w": 109,
			"h": 153
		},
		"res6": {
			"x": 261,
			"y": 0,
			"w": 119,
			"h": 153
		},
		"res7": {
			"x": 119,
			"y": 0,
			"w": 142,
			"h": 152
		},
		"res8": {
			"x": 0,
			"y": 0,
			"w": 119,
			"h": 161
		}
	}
}