{
    "mc": {
        "body982_1_2d": {
            "frameRate": 20,
            "frames": [
                {
                    "res": "00010.png",
                    "x": -54.0,
                    "y": -135.0
                },
                {
                    "res": "00011.png",
                    "x": -59.0,
                    "y": -131.0
                },
                {
                    "res": "00012.png",
                    "x": -73.0,
                    "y": -127.0
                },
                {
                    "res": "00013.png",
                    "x": -122.0,
                    "y": -77.0
                },
                {
                    "res": "00014.png",
                    "x": -130.0,
                    "y": -46.0
                }
            ]
        }
    },
    "res": {
        "00010.png": {
            "x": 0,
            "y": 0,
            "w": 95,
            "h": 144
        },
        "00011.png": {
            "x": 95,
            "y": 0,
            "w": 116,
            "h": 140
        },
        "00012.png": {
            "x": 211,
            "y": 0,
            "w": 105,
            "h": 137
        },
        "00013.png": {
            "x": 316,
            "y": 0,
            "w": 149,
            "h": 86
        },
        "00014.png": {
            "x": 465,
            "y": 0,
            "w": 167,
            "h": 90
        }
    }
}