{"mc": {"body962_0_3c": {"frameRate": 20, "frames": [{"res": "00025", "x": -45, "y": -126}, {"res": "00026", "x": -42, "y": -119}, {"res": "00027", "x": -40, "y": -131}, {"res": "00028", "x": -41, "y": -131}, {"res": "00029", "x": -41, "y": -131}, {"res": "00030", "x": -42, "y": -124}, {"res": "00031", "x": -46, "y": -119}, {"res": "00024", "x": -51, "y": -117}]}}, "res": {"00024": {"x": 0, "y": 0, "w": 101, "h": 138}, "00025": {"x": 101, "y": 0, "w": 88, "h": 144}, "00026": {"x": 189, "y": 0, "w": 87, "h": 132}, "00027": {"x": 276, "y": 0, "w": 87, "h": 146}, "00028": {"x": 363, "y": 0, "w": 91, "h": 153}, "00029": {"x": 454, "y": 0, "w": 94, "h": 157}, "00030": {"x": 548, "y": 0, "w": 95, "h": 156}, "00031": {"x": 643, "y": 0, "w": 100, "h": 154}}}