{
    "mc": {
        "body2208888_1_1d": {
            "frameRate": 20,
            "frames": [
                {
                    "res": "00005.png",
                    "x": -93.0,
                    "y": -143.0
                },
                {
                    "res": "00006.png",
                    "x": -75.0,
                    "y": -138.0
                },
                {
                    "res": "00007.png",
                    "x": -104.0,
                    "y": -115.0
                },
                {
                    "res": "00008.png",
                    "x": -109.0,
                    "y": -93.0
                },
                {
                    "res": "00009.png",
                    "x": -113.0,
                    "y": -58.0
                }
            ]
        }
    },
    "res": {
        "00005.png": {
            "x": 0,
            "y": 0,
            "w": 143,
            "h": 207
        },
        "00006.png": {
            "x": 143,
            "y": 0,
            "w": 127,
            "h": 197
        },
        "00007.png": {
            "x": 270,
            "y": 0,
            "w": 147,
            "h": 192
        },
        "00008.png": {
            "x": 417,
            "y": 0,
            "w": 189,
            "h": 150
        },
        "00009.png": {
            "x": 606,
            "y": 0,
            "w": 193,
            "h": 130
        }
    }
}