{
    "mc": {
        "body980_1_4a": {
            "frameRate": 15,
            "frames": [
                {
                    "res": "00037.png",
                    "x": -175.0,
                    "y": -246.0
                },
                {
                    "res": "00038.png",
                    "x": -134.0,
                    "y": -239.0
                },
                {
                    "res": "00039.png",
                    "x": -165.0,
                    "y": -182.0
                },
                {
                    "res": "00040.png",
                    "x": -95.0,
                    "y": -161.0
                },
                {
                    "res": "00041.png",
                    "x": -93.0,
                    "y": -155.0
                },
                {
                    "res": "00042.png",
                    "x": -94.0,
                    "y": -136.0
                },
                {
                    "res": "00043.png",
                    "x": -138.0,
                    "y": -170.0
                },
                {
                    "res": "00044.png",
                    "x": -167.0,
                    "y": -310.0
                },
                {
                    "res": "00036.png",
                    "x": -178.0,
                    "y": -240.0
                }
            ]
        }
    },
    "res": {
        "00036.png": {
            "x": 0,
            "y": 0,
            "w": 268,
            "h": 280
        },
        "00037.png": {
            "x": 268,
            "y": 0,
            "w": 272,
            "h": 287
        },
        "00038.png": {
            "x": 540,
            "y": 0,
            "w": 273,
            "h": 281
        },
        "00039.png": {
            "x": 813,
            "y": 0,
            "w": 253,
            "h": 250
        },
        "00040.png": {
            "x": 1066,
            "y": 0,
            "w": 236,
            "h": 308
        },
        "00041.png": {
            "x": 1302,
            "y": 0,
            "w": 234,
            "h": 302
        },
        "00042.png": {
            "x": 1536,
            "y": 0,
            "w": 284,
            "h": 289
        },
        "00043.png": {
            "x": 1820,
            "y": 0,
            "w": 227,
            "h": 270
        },
        "00044.png": {
            "x": 2047,
            "y": 0,
            "w": 238,
            "h": 352
        }
    }
}