{"mc":{
	"body921_0_3r":{
		"frameRate":12,
		"events":[
			
			],
		"frames":[
			
			{
			"res":"D1819723",
			"x":-31,
			"y":-105
			},
			{
			"res":"D691B26C",
			"x":-37,
			"y":-106
			},
			{
			"res":"71CFD3A",
			"x":-39,
			"y":-105
			},
			{
			"res":"21A1C78E",
			"x":-25,
			"y":-103
			},
			{
			"res":"35A7761A",
			"x":-37,
			"y":-105
			},
			{
			"res":"33DDE1F1",
			"x":-44,
			"y":-106
			},
			{
			"res":"365790C8",
			"x":-42,
			"y":-106
			},
			{
			"res":"35076831",
			"x":-33,
			"y":-104
			}
			]
}},
	"res":{
		"35076831":{"x":195,"y":98,"w":54,"h":101},
		"365790C8":{"x":131,"y":0,"w":64,"h":109},
		"21A1C78E":{"x":0,"y":110,"w":46,"h":103},
		"D1819723":{"x":195,"y":0,"w":58,"h":98},
		"33DDE1F1":{"x":64,"y":0,"w":67,"h":105},
		"71CFD3A":{"x":0,"y":0,"w":64,"h":110},
		"35A7761A":{"x":128,"y":109,"w":54,"h":94},
		"D691B26C":{"x":64,"y":105,"w":64,"h":108}
	}}