{"mc":{
	"body003_1_0a":{
		"frameRate":15,
		"events":[
			
			],
		"frames":[
			
			{
			"res":"F48152C1",
			"x":-25,
			"y":-89
			},
			{
			"res":"BA9772C4",
			"x":-25,
			"y":-79
			},
			{
			"res":"1CF33626",
			"x":-28,
			"y":-107
			},
			{
			"res":"C27604A1",
			"x":-39,
			"y":-122
			},
			{
			"res":"5B74D7DF",
			"x":-36,
			"y":-93
			},
			{
			"res":"9C37E2A5",
			"x":-32,
			"y":-97
			},
			{
			"res":"1BE676CB",
			"x":-28,
			"y":-94
			}
			]
}},
	"res":{
		"1BE676CB":{"x":66,"y":0,"w":67,"h":113},
		"5B74D7DF":{"x":133,"y":0,"w":61,"h":114},
		"1CF33626":{"x":66,"y":113,"w":51,"h":125},
		"BA9772C4":{"x":176,"y":119,"w":45,"h":98},
		"9C37E2A5":{"x":194,"y":0,"w":57,"h":119},
		"F48152C1":{"x":117,"y":114,"w":59,"h":108},
		"C27604A1":{"x":0,"y":0,"w":66,"h":139}
	}}