{"mc": {"body958_1_0s": {"frameRate": 10, "frames": [{"res": "00000", "x": -93, "y": -170}, {"res": "00001", "x": -83, "y": -175}, {"res": "00002", "x": -81, "y": -172}, {"res": "00003", "x": -82, "y": -171}, {"res": "00004", "x": -84, "y": -166}]}}, "res": {"00000": {"x": 0, "y": 0, "w": 184, "h": 197}, "00001": {"x": 184, "y": 0, "w": 163, "h": 202}, "00002": {"x": 347, "y": 0, "w": 164, "h": 205}, "00003": {"x": 511, "y": 0, "w": 165, "h": 204}, "00004": {"x": 676, "y": 0, "w": 168, "h": 192}}}