{"mc":{"body929_0_0r":{"frameRate":12,"frames":[{"res":"113","x":-28,"y":-107},{"res":"114","x":-27,"y":-108},{"res":"115","x":-28,"y":-106},{"res":"116","x":-29,"y":-105},{"res":"117","x":-28,"y":-107},{"res":"118","x":-26,"y":-108},{"res":"119","x":-26,"y":-106},{"res":"120","x":-27,"y":-105}]}},"res":{"113":{"x":0,"y":0,"w":56,"h":123},"114":{"x":56,"y":0,"w":55,"h":123},"115":{"x":111,"y":0,"w":56,"h":108},"116":{"x":167,"y":0,"w":58,"h":112},"117":{"x":225,"y":0,"w":56,"h":124},"118":{"x":281,"y":0,"w":53,"h":124},"119":{"x":334,"y":0,"w":54,"h":112},"120":{"x":388,"y":0,"w":57,"h":112}}}