{"mc":{
	"body974_suitinEff_12":{
		"frameRate":6,
		"labels":[
			{"name":"body974_suitinEff_12","frame":1,"end":5}
			
			],
		"events":[
			
			],
		"frames":[
			
			{
			"res":"10009",
			"x":-304,
			"y":-469
			},
			{
			"res":"10010",
			"x":-315,
			"y":-484
			},
			{
			"res":"10011",
			"x":-351,
			"y":-432
			},
			{
			"res":"10012",
			"x":-352,
			"y":-424
			},
			{
			"res":"10013",
			"x":-354,
			"y":-430
			}
			]
}},
	"res":{
		"10009":{"x":1394,"y":740,"w":646,"h":750},
		"10010":{"x":729,"y":755,"w":665,"h":774},
		"10011":{"x":749,"y":0,"w":720,"h":740},
		"10012":{"x":0,"y":755,"w":729,"h":743},
		"10013":{"x":0,"y":0,"w":749,"h":755}
	}}