{"mc":{
	"body935_1_eff":{
		"frameRate":6,
		"labels":[
			{"name":"body935_1_eff","frame":1,"end":6}
			
			],
		"events":[
			
			],
		"frames":[
			
			{
			"res":"00000",
			"x":-160,
			"y":-200
			},
			{
			"res":"00001",
			"x":-154,
			"y":-202
			},
			{
			"res":"00002",
			"x":-152,
			"y":-201
			},
			{
			"res":"00003",
			"x":-164,
			"y":-194
			},
			{
			"res":"00004",
			"x":-161,
			"y":-191
			},
			{
			"res":"00005",
			"x":-154,
			"y":-201
			}
			]
}},
	"res":{
		"00003":{"x":0,"y":0,"w":328,"h":521},
		"00004":{"x":659,"y":0,"w":327,"h":518},
		"00001":{"x":653,"y":520,"w":321,"h":520},
		"00005":{"x":330,"y":520,"w":321,"h":527},
		"00002":{"x":0,"y":523,"w":318,"h":528},
		"00000":{"x":330,"y":0,"w":327,"h":518}
	}}