{"mc":{
	"chenghao133":{
		"frameRate":10,
		"events":[
			
			],
		"frames":[
			
			{
			"res":"C7BFD56C",
			"x":-121,
			"y":-37
			},
			{
			"res":"1EE39CC4",
			"x":-121,
			"y":-37
			},
			{
			"res":"815AA99B",
			"x":-121,
			"y":-38
			},
			{
			"res":"6662E79",
			"x":-121,
			"y":-39
			},
			{
			"res":"EE276C27",
			"x":-121,
			"y":-39
			},
			{
			"res":"C316DBA4",
			"x":-121,
			"y":-38
			},
			{
			"res":"AF3785CF",
			"x":-121,
			"y":-37
			},
			{
			"res":"D5353CF0",
			"x":-121,
			"y":-37
			}
			]
}},
	"res":{
		"1EE39CC4":{"x":0,"y":155,"w":249,"h":76},
		"815AA99B":{"x":0,"y":78,"w":249,"h":77},
		"C7BFD56C":{"x":0,"y":231,"w":249,"h":76},
		"D5353CF0":{"x":249,"y":231,"w":249,"h":76},
		"EE276C27":{"x":0,"y":0,"w":249,"h":78},
		"AF3785CF":{"x":249,"y":155,"w":249,"h":76},
		"6662E79":{"x":249,"y":0,"w":249,"h":78},
		"C316DBA4":{"x":249,"y":78,"w":249,"h":77}
	}}