{"mc":{
	"zhanling2014_4r":{
		"frameRate":8,
		"labels":[
			{"name":"zhanling2014_4r","frame":1,"end":6}
			
			],
		"events":[
			
			],
		"frames":[
			
			{
			"res":"00024",
			"x":-448,
			"y":-335
			},
			{
			"res":"00025",
			"x":-444,
			"y":-347
			},
			{
			"res":"00026",
			"x":-442,
			"y":-361
			},
			{
			"res":"00027",
			"x":-430,
			"y":-374
			},
			{
			"res":"00028",
			"x":-441,
			"y":-360
			},
			{
			"res":"00029",
			"x":-442,
			"y":-350
			}
			]
}},
	"res":{
		"00025":{"x":0,"y":1382,"w":882,"h":334},
		"00029":{"x":0,"y":1042,"w":878,"h":340},
		"00026":{"x":0,"y":0,"w":878,"h":346},
		"00024":{"x":0,"y":1716,"w":890,"h":325},
		"00028":{"x":0,"y":701,"w":876,"h":341},
		"00027":{"x":0,"y":346,"w":854,"h":355}
	}}