{
    "mc": {
        "zhanling2037_2r": {
            "frameRate": 12,
            "frames": [
                {
                    "res": "00012.png",
                    "x": -168.5,
                    "y": -485.5
                },
                {
                    "res": "00013.png",
                    "x": -145.5,
                    "y": -497.5
                },
                {
                    "res": "00014.png",
                    "x": -98.5,
                    "y": -499.5
                },
                {
                    "res": "00015.png",
                    "x": -99.5,
                    "y": -490.5
                },
                {
                    "res": "00016.png",
                    "x": -112.5,
                    "y": -491.5
                },
                {
                    "res": "00017.png",
                    "x": -146.5,
                    "y": -478.5
                }
            ]
        }
    },
    "res": {
        "00012.png": {
            "x": 0,
            "y": 0,
            "w": 370,
            "h": 563
        },
        "00013.png": {
            "x": 370,
            "y": 0,
            "w": 348,
            "h": 571
        },
        "00014.png": {
            "x": 718,
            "y": 0,
            "w": 309,
            "h": 584
        },
        "00015.png": {
            "x": 1027,
            "y": 0,
            "w": 317,
            "h": 576
        },
        "00016.png": {
            "x": 1344,
            "y": 0,
            "w": 329,
            "h": 536
        },
        "00017.png": {
            "x": 1673,
            "y": 0,
            "w": 354,
            "h": 533
        }
    }
}