{"mc":{
	"zhanling2015_3s":{
		"frameRate":12,
		"labels":[
			{"name":"zhanling2015_3s","frame":1,"end":6}
			
			],
		"events":[
			
			],
		"frames":[
			
			{
			"res":"00018",
			"x":-236,
			"y":-398
			},
			{
			"res":"00019",
			"x":-219,
			"y":-402
			},
			{
			"res":"00020",
			"x":-208,
			"y":-414
			},
			{
			"res":"00021",
			"x":-217,
			"y":-428
			},
			{
			"res":"00022",
			"x":-236,
			"y":-438
			},
			{
			"res":"00023",
			"x":-248,
			"y":-444
			}
			]
}},
	"res":{
		"00019":{"x":0,"y":1425,"w":417,"h":455},
		"00022":{"x":444,"y":0,"w":429,"h":506},
		"00020":{"x":412,"y":951,"w":405,"h":474},
		"00021":{"x":0,"y":494,"w":412,"h":502},
		"00018":{"x":412,"y":506,"w":434,"h":445},
		"00023":{"x":0,"y":0,"w":444,"h":494}
	}}