{"mc":{
	"wing108_1c":{
		"frameRate":15,
		"events":[
			
			],
		"frames":[
			
			{
			"res":"ED33FAAA",
			"x":-56,
			"y":-125
			},
			{
			"res":"37BF0B7C",
			"x":-58,
			"y":-128
			},
			{
			"res":"403407DD",
			"x":-61,
			"y":-126
			},
			{
			"res":"10495B6",
			"x":-60,
			"y":-120
			},
			{
			"res":"8B892C5F",
			"x":-56,
			"y":-123
			},
			{
			"res":"43D6AAEC",
			"x":-57,
			"y":-126
			},
			{
			"res":"B73E94B5",
			"x":-36,
			"y":-134
			}
			]
}},
	"res":{
		"37BF0B7C":{"x":91,"y":96,"w":91,"h":99},
		"43D6AAEC":{"x":0,"y":0,"w":91,"h":100},
		"8B892C5F":{"x":0,"y":100,"w":87,"h":103},
		"403407DD":{"x":87,"y":195,"w":83,"h":102},
		"ED33FAAA":{"x":91,"y":0,"w":94,"h":96},
		"10495B6":{"x":170,"y":195,"w":83,"h":100},
		"B73E94B5":{"x":185,"y":0,"w":35,"h":113}
	}}