{"mc":{
	"wing126_0r":{
		"frameRate":12,
		"events":[
			
			],
		"frames":[
			
			{
			"res":"81B7B614",
			"x":-91,
			"y":-157
			},
			{
			"res":"E7861E82",
			"x":-99,
			"y":-155
			},
			{
			"res":"F04EA469",
			"x":-95,
			"y":-153
			},
			{
			"res":"2FA69816",
			"x":-92,
			"y":-177
			},
			{
			"res":"928603AD",
			"x":-90,
			"y":-181
			},
			{
			"res":"C404147F",
			"x":-89,
			"y":-170
			},
			{
			"res":"73A189DF",
			"x":-90,
			"y":-165
			},
			{
			"res":"B5D6BC38",
			"x":-93,
			"y":-179
			}
			]
}},
	"res":{
		"2FA69816":{"x":0,"y":178,"w":182,"h":176},
		"81B7B614":{"x":556,"y":347,"w":181,"h":156},
		"C404147F":{"x":182,"y":179,"w":176,"h":168},
		"F04EA469":{"x":368,"y":347,"w":188,"h":151},
		"B5D6BC38":{"x":0,"y":0,"w":180,"h":178},
		"928603AD":{"x":182,"y":0,"w":178,"h":179},
		"E7861E82":{"x":0,"y":354,"w":192,"h":153},
		"73A189DF":{"x":192,"y":347,"w":176,"h":164}
	}}