{"mc":{
	"wing125_0s":{
		"frameRate":6,
		"events":[
			
			],
		"frames":[
			
			{
			"res":"9A2C1D16",
			"x":-93,
			"y":-144
			},
			{
			"res":"D28CB78F",
			"x":-94,
			"y":-146
			},
			{
			"res":"5E27EBDD",
			"x":-94,
			"y":-144
			},
			{
			"res":"7BE51131",
			"x":-93,
			"y":-137
			}
			]
}},
	"res":{
		"9A2C1D16":{"x":185,"y":132,"w":183,"h":131},
		"5E27EBDD":{"x":185,"y":0,"w":184,"h":132},
		"D28CB78F":{"x":0,"y":0,"w":185,"h":134},
		"7BE51131":{"x":0,"y":134,"w":183,"h":125}
	}}