{"mc":{
	"wing123_4s":{
		"frameRate":6,
		"events":[
			
			],
		"frames":[
			
			{
			"res":"B53A584C",
			"x":-80,
			"y":-168
			},
			{
			"res":"95BEE833",
			"x":-79,
			"y":-155
			},
			{
			"res":"D7601CBA",
			"x":-79,
			"y":-157
			},
			{
			"res":"73638FCA",
			"x":-77,
			"y":-158
			}
			]
}},
	"res":{
		"95BEE833":{"x":305,"y":126,"w":153,"h":124},
		"73638FCA":{"x":154,"y":126,"w":151,"h":127},
		"D7601CBA":{"x":154,"y":0,"w":153,"h":126},
		"B53A584C":{"x":0,"y":0,"w":154,"h":137}
	}}