{
	"mc": {
		"wing141_0d": {
			"frameRate": 20,
			"frames": [
				{
					"res": "res5",
					"x": -163,
					"y": -125
				},
				{
					"res": "res4",
					"x": -128,
					"y": -147
				},
				{
					"res": "res3",
					"x": -125,
					"y": -142
				},
				{
					"res": "res2",
					"x": -102,
					"y": -54
				},
				{
					"res": "res1",
					"x": -165,
					"y": -1
				}
			]
		}
	},
	"res": {
		"res1": {
			"x": 1018,
			"y": 0,
			"w": 328,
			"h": 90
		},
		"res2": {
			"x": 818,
			"y": 0,
			"w": 200,
			"h": 104
		},
		"res3": {
			"x": 572,
			"y": 0,
			"w": 246,
			"h": 159
		},
		"res4": {
			"x": 321,
			"y": 0,
			"w": 251,
			"h": 145
		},
		"res5": {
			"x": 0,
			"y": 0,
			"w": 321,
			"h": 126
		}
	}
}