{
    "mc": {
        "wing144_4s": {
            "frameRate": 10,
            "frames": [
                {
                    "res": "00020.png",
                    "x": -144.0,
                    "y": -196.0
                },
                {
                    "res": "00021.png",
                    "x": -143.0,
                    "y": -207.0
                },
                {
                    "res": "00022.png",
                    "x": -132.0,
                    "y": -201.0
                },
                {
                    "res": "00023.png",
                    "x": -137.0,
                    "y": -190.0
                },
                {
                    "res": "00024.png",
                    "x": -149.0,
                    "y": -187.0
                }
            ]
        }
    },
    "res": {
        "00020.png": {
            "x": 0,
            "y": 0,
            "w": 288,
            "h": 145
        },
        "00021.png": {
            "x": 288,
            "y": 0,
            "w": 287,
            "h": 153
        },
        "00022.png": {
            "x": 575,
            "y": 0,
            "w": 265,
            "h": 149
        },
        "00023.png": {
            "x": 840,
            "y": 0,
            "w": 275,
            "h": 143
        },
        "00024.png": {
            "x": 1115,
            "y": 0,
            "w": 299,
            "h": 139
        }
    }
}