{
	"mc": {
		"wing135_4s": {
			"frameRate": 10,
			"frames": [
				{
					"res": "res5",
					"x": -188,
					"y": -210
				},
				{
					"res": "res4",
					"x": -194,
					"y": -207
				},
				{
					"res": "res3",
					"x": -188,
					"y": -215
				},
				{
					"res": "res2",
					"x": -185,
					"y": -220
				},
				{
					"res": "res1",
					"x": -174,
					"y": -218
				}
			]
		}
	},
	"res": {
		"res1": {
			"x": 1534,
			"y": 0,
			"w": 351,
			"h": 179
		},
		"res2": {
			"x": 1167,
			"y": 0,
			"w": 367,
			"h": 175
		},
		"res3": {
			"x": 781,
			"y": 0,
			"w": 386,
			"h": 180
		},
		"res4": {
			"x": 379,
			"y": 0,
			"w": 402,
			"h": 175
		},
		"res5": {
			"x": 0,
			"y": 0,
			"w": 379,
			"h": 172
		}
	}
}