{
    "mc": {
        "wing161_0s": {
            "frameRate": 10,
            "frames": [
                {
                    "res": "00000.png",
                    "x": -105.0,
                    "y": -146.0
                },
                {
                    "res": "00001.png",
                    "x": -105.0,
                    "y": -146.0
                },
                {
                    "res": "00002.png",
                    "x": -121.0,
                    "y": -147.0
                },
                {
                    "res": "00003.png",
                    "x": -120.0,
                    "y": -146.0
                },
                {
                    "res": "00004.png",
                    "x": -115.0,
                    "y": -146.0
                }
            ]
        }
    },
    "res": {
        "00000.png": {
            "x": 0,
            "y": 0,
            "w": 223,
            "h": 182
        },
        "00001.png": {
            "x": 223,
            "y": 0,
            "w": 226,
            "h": 161
        },
        "00002.png": {
            "x": 449,
            "y": 0,
            "w": 243,
            "h": 168
        },
        "00003.png": {
            "x": 692,
            "y": 0,
            "w": 246,
            "h": 168
        },
        "00004.png": {
            "x": 938,
            "y": 0,
            "w": 236,
            "h": 181
        }
    }
}